{
  "configs": [
    "api_provedor.xml"
  ],
  "secureProperties": [],
  "redeploymentEnabled": true,
  "name": "e59abd4d-0dc2-4639-9f32-21aa3f9fa542:porvedor:1.0.2",
  "minMuleVersion": "4.4.0",
  "requiredProduct": "MULE_EE",
  "classLoaderModelLoaderDescriptor": {
    "id": "mule",
    "attributes": {
      "exportedPackages": [],
      "exportedResources": [
        "api/api_provedor.raml",
        "api_provedor.xml",
        "application-types.xml",
        "log4j2.xml"
      ]
    }
  },
  "bundleDescriptorLoader": {
    "id": "mule",
    "attributes": {}
  }
}